nubilum/__init__.py
nubilum/attr/__init__.py
nubilum/attr/nubilum_integrated_gradients.py
nubilum/attr/nubilum_saliency.py
nubilum/forward/__init__.py
nubilum/forward/nubilum_forward.py
nubilum/utils/__init__.py
nubilum/utils/nubilum_utils.py
Nubilum-0.1.1.dist-info/LICENSE
Nubilum-0.1.1.dist-info/METADATA
Nubilum-0.1.1.dist-info/WHEEL
Nubilum-0.1.1.dist-info/top_level.txt
Nubilum-0.1.1.dist-info/RECORD
